sintel/__init__.py
sintel/cli.py
sintel/core.py
sintel/data.py
sintel/model.py
sintel/routes.py
sintel/swagger.py
sintel/utils.py
sintel/db/__init__.py
sintel/db/base.py
sintel/db/explorer.py
sintel/db/schema.py
sintel/db/utils.py
sintel/resources/__init__.py
sintel/resources/auth_utils.py
sintel/resources/comment.py
sintel/resources/datarun.py
sintel/resources/dataset.py
sintel/resources/event.py
sintel/resources/experiment.py
sintel/resources/google_auth.py
sintel/resources/pipeline.py
sintel/resources/signal.py
sintel/resources/test.py
sintel/resources/user.py
sintel/resources/computing/__init__.py
sintel/resources/computing/similar_windows.py
sintel/resources/computing/utils/__init__.py
sintel/resources/computing/utils/layout.py
sintel/resources/computing/utils/search_similars.py
sintel/resources/computing/utils/search_similars_bk.py
sintel/resources/computing/utils/signal_distance.py
sintel-0.1.0.dev0.dist-info/LICENSE
sintel-0.1.0.dev0.dist-info/METADATA
sintel-0.1.0.dev0.dist-info/WHEEL
sintel-0.1.0.dev0.dist-info/entry_points.txt
sintel-0.1.0.dev0.dist-info/top_level.txt
sintel-0.1.0.dev0.dist-info/RECORD
