Metadata-Version: 2.1
Name: sintel
Version: 0.1.0.dev0
Summary: Sintel(Signal Intelligence) provides Restful APIs to processmassive signal data for anomaly analysis in an efficientand user-friendly way
Home-page: https://github.com/signals-dev/sintel
Author: MIT Data To AI Lab
Author-email: dailabmit@gmail.com
License: MIT license
Keywords: sintel
Platform: UNKNOWN
Classifier: Development Status :: 2 - Pre-Alpha
Classifier: Intended Audience :: Developers
Classifier: License :: OSI Approved :: MIT License
Classifier: Natural Language :: English
Classifier: Programming Language :: Python :: 3
Classifier: Programming Language :: Python :: 3.6
Requires-Python: >=3.6
Requires-Dist: Click (>=6.0)
Requires-Dist: termcolor (==1.1.0)
Requires-Dist: PyYAML (==5.1)
Requires-Dist: passlib (==1.7.2)
Requires-Dist: tqdm (==4.48.0)
Requires-Dist: oauthlib (==3.1.0)
Requires-Dist: pyOpenSSL (==19.1.0)
Requires-Dist: numpy (<1.17,>=1.15.4)
Requires-Dist: pandas (<0.25,>=0.23.4)
Requires-Dist: dtw (>=1.4.0)
Requires-Dist: scikit-learn (>=0.22.2)
Requires-Dist: pyts (==0.10.0)
Requires-Dist: numba (==0.50.1)
Requires-Dist: Flask (==1.0.2)
Requires-Dist: Flask-Cors (==3.0.7)
Requires-Dist: Flask-RESTful (==0.3.7)
Requires-Dist: requests (==2.24.0)
Requires-Dist: Werkzeug (==0.15.3)
Requires-Dist: gevent (==1.2.2)
Requires-Dist: flasgger (==0.9.5)
Requires-Dist: mongoengine (<0.17,>=0.16.3)
Requires-Dist: pymongo (<4,>=3.7.2)
Provides-Extra: dev
Requires-Dist: bumpversion (>=0.5.3) ; extra == 'dev'
Requires-Dist: pip (>=9.0.1) ; extra == 'dev'
Requires-Dist: watchdog (>=0.8.3) ; extra == 'dev'
Requires-Dist: m2r (>=0.2.0) ; extra == 'dev'
Requires-Dist: Sphinx (>=1.7.1) ; extra == 'dev'
Requires-Dist: sphinx-rtd-theme (>=0.2.4) ; extra == 'dev'
Requires-Dist: flake8 (>=3.5.0) ; extra == 'dev'
Requires-Dist: isort (<5.0.0,>=4.3.4) ; extra == 'dev'
Requires-Dist: autoflake (>=1.1) ; extra == 'dev'
Requires-Dist: autopep8 (>=1.3.5) ; extra == 'dev'
Requires-Dist: twine (>=1.10.0) ; extra == 'dev'
Requires-Dist: wheel (>=0.30.0) ; extra == 'dev'
Requires-Dist: jupyter (>=1.0.0) ; extra == 'dev'
Requires-Dist: coverage (>=4.5.1) ; extra == 'dev'
Requires-Dist: pytest (>=4.0.2) ; extra == 'dev'
Requires-Dist: tox (>=2.9.1) ; extra == 'dev'
Requires-Dist: pytest-flask (>=0.14.0) ; extra == 'dev'
Requires-Dist: pytest-xdist (>=1.25.0) ; extra == 'dev'
Provides-Extra: test
Requires-Dist: coverage (>=4.5.1) ; extra == 'test'
Requires-Dist: pytest (>=4.0.2) ; extra == 'test'
Requires-Dist: tox (>=2.9.1) ; extra == 'test'
Requires-Dist: pytest-flask (>=0.14.0) ; extra == 'test'
Requires-Dist: pytest-xdist (>=1.25.0) ; extra == 'test'
